taskiq/__init__.py
taskiq/__main__.py
taskiq/abc/__init__.py
taskiq/abc/broker.py
taskiq/abc/cmd.py
taskiq/abc/formatter.py
taskiq/abc/middleware.py
taskiq/abc/result_backend.py
taskiq/abc/schedule_source.py
taskiq/abc/serializer.py
taskiq/acks.py
taskiq/api/__init__.py
taskiq/api/receiver.py
taskiq/api/scheduler.py
taskiq/brokers/__init__.py
taskiq/brokers/inmemory_broker.py
taskiq/brokers/shared_broker.py
taskiq/brokers/zmq_broker.py
taskiq/cli/__init__.py
taskiq/cli/common_args.py
taskiq/cli/scheduler/__init__.py
taskiq/cli/scheduler/args.py
taskiq/cli/scheduler/cmd.py
taskiq/cli/scheduler/run.py
taskiq/cli/utils.py
taskiq/cli/watcher.py
taskiq/cli/worker/__init__.py
taskiq/cli/worker/args.py
taskiq/cli/worker/cmd.py
taskiq/cli/worker/log_collector.py
taskiq/cli/worker/process_manager.py
taskiq/cli/worker/run.py
taskiq/compat.py
taskiq/context.py
taskiq/decor.py
taskiq/depends/progress_tracker.py
taskiq/events.py
taskiq/exceptions.py
taskiq/formatters/__init__.py
taskiq/formatters/json_formatter.py
taskiq/formatters/proxy_formatter.py
taskiq/funcs.py
taskiq/kicker.py
taskiq/labels.py
taskiq/message.py
taskiq/middlewares/__init__.py
taskiq/middlewares/prometheus_middleware.py
taskiq/middlewares/simple_retry_middleware.py
taskiq/middlewares/smart_retry_middleware.py
taskiq/middlewares/taskiq_admin_middleware.py
taskiq/py.typed
taskiq/receiver/__init__.py
taskiq/receiver/params_parser.py
taskiq/receiver/receiver.py
taskiq/result/__init__.py
taskiq/result/result.py
taskiq/result_backends/__init__.py
taskiq/result_backends/dummy.py
taskiq/schedule_sources/__init__.py
taskiq/schedule_sources/label_based.py
taskiq/scheduler/__init__.py
taskiq/scheduler/created_schedule.py
taskiq/scheduler/merge_functions.py
taskiq/scheduler/scheduled_task/__init__.py
taskiq/scheduler/scheduled_task/cron_spec.py
taskiq/scheduler/scheduled_task/v1.py
taskiq/scheduler/scheduled_task/v2.py
taskiq/scheduler/scheduler.py
taskiq/serialization.py
taskiq/serializers/__init__.py
taskiq-0.11.19.dist-info/METADATA
taskiq-0.11.19.dist-info/WHEEL
taskiq-0.11.19.dist-info/entry_points.txt
taskiq-0.11.19.dist-info/licenses/LICENSE
taskiq-0.11.19.dist-info/RECORD
