Metadata-Version: 2.4
Name: taskiq
Version: 0.11.19
Summary: Distributed task queue with full async support
License: LICENSE
License-File: LICENSE
Keywords: taskiq,tasks,distributed,async
Author: Pavel Kirilin
Author-email: win10@list.ru
Maintainer: Pavel Kirilin
Maintainer-email: win10@list.ru
Requires-Python: >=3.9,<4.0
Classifier: Development Status :: 3 - Alpha
Classifier: Intended Audience :: Developers
Classifier: License :: Other/Proprietary License
Classifier: Operating System :: OS Independent
Classifier: Programming Language :: Python
Classifier: Programming Language :: Python :: 3
Classifier: Programming Language :: Python :: 3.9
Classifier: Programming Language :: Python :: 3.10
Classifier: Programming Language :: Python :: 3.11
Classifier: Programming Language :: Python :: 3.12
Classifier: Programming Language :: Python :: 3.13
Classifier: Programming Language :: Python :: 3.14
Classifier: Programming Language :: Python :: 3 :: Only
Classifier: Programming Language :: Python :: 3.8
Classifier: Topic :: System :: Networking
Classifier: Typing :: Typed
Provides-Extra: cbor
Provides-Extra: metrics
Provides-Extra: msgpack
Provides-Extra: orjson
Provides-Extra: reload
Provides-Extra: uv
Provides-Extra: zmq
Requires-Dist: aiohttp (>=3,<4)
Requires-Dist: anyio (>=3)
Requires-Dist: cbor2 (>=5,<6) ; extra == "cbor"
Requires-Dist: gitignore-parser (>=0,<1) ; extra == "reload"
Requires-Dist: importlib-metadata
Requires-Dist: izulu (==0.50.0)
Requires-Dist: msgpack (>=1.0.7,<2.0.0) ; extra == "msgpack"
Requires-Dist: orjson (>=3,<4) ; extra == "orjson"
Requires-Dist: packaging (>=19)
Requires-Dist: prometheus_client (>=0,<1) ; extra == "metrics"
Requires-Dist: pycron (>=3.0.0,<4.0.0)
Requires-Dist: pydantic (>=1.0,<=3.0)
Requires-Dist: pytz
Requires-Dist: pyzmq (>=26,<27) ; extra == "zmq"
Requires-Dist: taskiq_dependencies (>=1.3.1,<2)
Requires-Dist: typing-extensions (>=3.10.0.0)
Requires-Dist: uvloop (>=0.16.0,<1) ; (sys_platform != "win32") and (extra == "uv")
Requires-Dist: watchdog (>=4,<5) ; extra == "reload"
Project-URL: Documentation, https://taskiq-python.github.io/
Project-URL: Homepage, https://taskiq-python.github.io/
Project-URL: Repository, https://github.com/taskiq-python/taskiq
